xenopt/__init__.py
xenopt/tb_parameters.py
xenopt/thermobarometers.py
xenopt/xenolith_dataTemplate.csv
xenopt-0.2.6.dist-info/WHEEL
xenopt-0.2.6.dist-info/METADATA
xenopt-0.2.6.dist-info/RECORD
